odoo8_addon_account_move_reconcile_helper-8.0.1.1.0.99.dev3-py2.7-nspkg.pth
odoo8_addon_account_move_reconcile_helper-8.0.1.1.0.99.dev3.dist-info/METADATA
odoo8_addon_account_move_reconcile_helper-8.0.1.1.0.99.dev3.dist-info/RECORD
odoo8_addon_account_move_reconcile_helper-8.0.1.1.0.99.dev3.dist-info/WHEEL
odoo8_addon_account_move_reconcile_helper-8.0.1.1.0.99.dev3.dist-info/namespace_packages.txt
odoo8_addon_account_move_reconcile_helper-8.0.1.1.0.99.dev3.dist-info/top_level.txt
odoo_addons/account_move_reconcile_helper/README.rst
odoo_addons/account_move_reconcile_helper/__init__.py
odoo_addons/account_move_reconcile_helper/__openerp__.py
odoo_addons/account_move_reconcile_helper/post_install.py
odoo_addons/account_move_reconcile_helper/i18n/account_move_reconcile_helper.pot
odoo_addons/account_move_reconcile_helper/i18n/ar.po
odoo_addons/account_move_reconcile_helper/i18n/bs.po
odoo_addons/account_move_reconcile_helper/i18n/ca.po
odoo_addons/account_move_reconcile_helper/i18n/cs.po
odoo_addons/account_move_reconcile_helper/i18n/de.po
odoo_addons/account_move_reconcile_helper/i18n/en_GB.po
odoo_addons/account_move_reconcile_helper/i18n/es.po
odoo_addons/account_move_reconcile_helper/i18n/es_CR.po
odoo_addons/account_move_reconcile_helper/i18n/es_EC.po
odoo_addons/account_move_reconcile_helper/i18n/es_MX.po
odoo_addons/account_move_reconcile_helper/i18n/fr.po
odoo_addons/account_move_reconcile_helper/i18n/fr_CH.po
odoo_addons/account_move_reconcile_helper/i18n/gl.po
odoo_addons/account_move_reconcile_helper/i18n/hr.po
odoo_addons/account_move_reconcile_helper/i18n/hu.po
odoo_addons/account_move_reconcile_helper/i18n/id.po
odoo_addons/account_move_reconcile_helper/i18n/it.po
odoo_addons/account_move_reconcile_helper/i18n/ja.po
odoo_addons/account_move_reconcile_helper/i18n/lt.po
odoo_addons/account_move_reconcile_helper/i18n/mk.po
odoo_addons/account_move_reconcile_helper/i18n/mn.po
odoo_addons/account_move_reconcile_helper/i18n/nb.po
odoo_addons/account_move_reconcile_helper/i18n/nl.po
odoo_addons/account_move_reconcile_helper/i18n/nl_BE.po
odoo_addons/account_move_reconcile_helper/i18n/pt.po
odoo_addons/account_move_reconcile_helper/i18n/pt_BR.po
odoo_addons/account_move_reconcile_helper/i18n/pt_PT.po
odoo_addons/account_move_reconcile_helper/i18n/ro.po
odoo_addons/account_move_reconcile_helper/i18n/ro_RO.po
