Metadata-Version: 2.1
Name: odoo8-addon-account-move-reconcile-helper
Version: 8.0.1.1.0.99.dev3
Summary: Account Move Reconcile Helper
Home-page: http://acsone.eu
Author: ACSONE SA/NV,Odoo Community Association (OCA)
Author-email: support@odoo-community.org
License: AGPL-3
Platform: UNKNOWN
Classifier: Programming Language :: Python
Classifier: Framework :: Odoo
Classifier: License :: OSI Approved :: GNU Affero General Public License v3
Requires-Python: ~=2.7
Requires-Dist: odoo8-addon-web-option-auto-color
Requires-Dist: odoo (<9.0a,>=8.0a)
